vaxila/opentelemetry/util/__init__.py
vaxila/opentelemetry/util/_internal/exception_recorder.py
vaxila_opentelemetry_util-0.0.1.dist-info/METADATA
vaxila_opentelemetry_util-0.0.1.dist-info/WHEEL
vaxila_opentelemetry_util-0.0.1.dist-info/licenses/LICENSE
vaxila_opentelemetry_util-0.0.1.dist-info/RECORD
