Metadata-Version: 2.1
Name: vaxila-opentelemetry-util
Version: 0.0.1
Summary: OpenTelemetry utilities by Vaxila
Project-URL: Homepage, https://github.com/vaxila-labs/vaxila-python-opentelemetry-util
Project-URL: Bug Tracker, https://github.com/vaxila-labs/vaxila-python-opentelemetry-util/issues
Author-email: Vaxila Labs <hello@vaxila-labs.com>
License-File: LICENSE
Classifier: License :: OSI Approved :: MIT License
Classifier: Operating System :: OS Independent
Classifier: Programming Language :: Python :: 3
Requires-Python: >=3.7
Requires-Dist: opentelemetry-sdk~=1.12
